td/__init__.py
td/td.py
trialdesign-2.1.7.dist-info/COPYING
trialdesign-2.1.7.dist-info/METADATA
trialdesign-2.1.7.dist-info/WHEEL
trialdesign-2.1.7.dist-info/entry_points.txt
trialdesign-2.1.7.dist-info/top_level.txt
trialdesign-2.1.7.dist-info/RECORD
