Metadata-Version: 2.1
Name: trialdesign
Version: 2.1.7
Summary: Visualization of clinical study designs
Author: Rainer Strotmann
Author-email: rainer.strotmann@mailbox.org
License: GPL-3.0-or-later
Platform: UNKNOWN
Classifier: Programming Language :: Python :: 3
Classifier: Operating System :: OS Independent
Classifier: License :: OSI Approved :: GNU General Public License v3 or later (GPLv3+)
Requires-Python: >=3.7
License-File: COPYING
Requires-Dist: typer
Requires-Dist: pathlib2
Requires-Dist: CairoSVG
Requires-Dist: pycairo
Requires-Dist: rich
Requires-Dist: PyYAML
